{"engine1": "PrototypeV1Engine", "engine2": "StockfishEngine", "rounds": 10, "games": [{"color": false, "number_of_moves": 81, "time": 255.85704466300012, "result": -1}, {"color": true, "number_of_moves": 158, "time": 274.25241942100183, "result": -1}, {"color": true, "number_of_moves": 104, "time": 383.2799850729971, "result": -1}, {"color": true, "number_of_moves": 90, "time": 385.4039387019984, "result": -1}, {"color": false, "number_of_moves": 63, "time": 514.8210688730032, "result": -1}, {"color": true, "number_of_moves": 96, "time": 603.0571922639974, "result": -1}, {"color": false, "number_of_moves": 73, "time": 743.3061635829981, "result": -1}, {"color": false, "number_of_moves": 151, "time": 766.696333844, "result": -1}, {"color": false, "number_of_moves": 73, "time": 1465.5766389490018, "result": -1}, {"color": true, "number_of_moves": 76, "time": 2427.9083551509975, "result": -1}]}